__init__.py
micronuclai_labeling/__init__.py
micronuclai_labeling/__main__.py
micronuclai_labeling/_labeling_tool.py
micronuclAI_labeling-0.1.1.dist-info/LICENSE
micronuclAI_labeling-0.1.1.dist-info/METADATA
micronuclAI_labeling-0.1.1.dist-info/WHEEL
micronuclAI_labeling-0.1.1.dist-info/top_level.txt
micronuclAI_labeling-0.1.1.dist-info/RECORD
