Metadata-Version: 2.1
Name: micronuclAI_labeling
Version: 0.1.1
Summary: GUI tool for labeling micronuclei images
Author-email: "Miguel A. Ibarra-Arellano" <c180l058j@mozmail.com>
Project-URL: Homepage, https://github.com/SchapiroLabor/micronuclAI_labeling
Project-URL: Issues, https://github.com/SchapiroLabor/micronuclAI_labeling/issues
Keywords: micronuclei,labeling,gui
Classifier: Programming Language :: Python :: 3.9
Classifier: Programming Language :: Python :: 3.10
Classifier: Programming Language :: Python :: 3.11
Classifier: Operating System :: OS Independent
Classifier: Framework :: PySimpleGUI
Classifier: Intended Audience :: Science/Research
Classifier: License :: OSI Approved :: GNU Affero General Public License v3
Requires-Python: >=3.9
License-File: LICENSE
Requires-Dist: numpy
Requires-Dist: matplotlib
Requires-Dist: scikit-image
Requires-Dist: PySimpleGUI
Requires-Dist: mask2bbox
